odoo/addons/l10n_nl_mis_reports/README.rst
odoo/addons/l10n_nl_mis_reports/__init__.py
odoo/addons/l10n_nl_mis_reports/__manifest__.py
odoo/addons/l10n_nl_mis_reports/data/mis_report.xml
odoo/addons/l10n_nl_mis_reports/data/mis_report_kpi.xml
odoo/addons/l10n_nl_mis_reports/data/mis_report_style.xml
odoo/addons/l10n_nl_mis_reports/data/mis_report_subreport.xml
odoo/addons/l10n_nl_mis_reports/i18n/l10n_nl_mis_reports.pot
odoo/addons/l10n_nl_mis_reports/models/__init__.py
odoo/addons/l10n_nl_mis_reports/models/mis_report_instance.py
odoo/addons/l10n_nl_mis_reports/readme/CONTRIBUTORS.rst
odoo/addons/l10n_nl_mis_reports/readme/DESCRIPTION.rst
odoo/addons/l10n_nl_mis_reports/readme/ROADMAP.rst
odoo/addons/l10n_nl_mis_reports/readme/USAGE.rst
odoo/addons/l10n_nl_mis_reports/readme/newsfragments/.gitkeep
odoo/addons/l10n_nl_mis_reports/static/description/icon.png
odoo/addons/l10n_nl_mis_reports/static/description/index.html
odoo/addons/l10n_nl_mis_reports/static/src/css/l10n_nl_mis_reports.css
odoo/addons/l10n_nl_mis_reports/static/src/css/report.css
odoo/addons/l10n_nl_mis_reports/static/src/xml/l10n_nl_mis_reports.xml
odoo/addons/l10n_nl_mis_reports/tests/__init__.py
odoo/addons/l10n_nl_mis_reports/tests/test_l10n_nl_mis_reports.py
odoo/addons/l10n_nl_mis_reports/views/templates.xml
odoo13_addon_l10n_nl_mis_reports-13.0.1.1.0.dist-info/METADATA
odoo13_addon_l10n_nl_mis_reports-13.0.1.1.0.dist-info/WHEEL
odoo13_addon_l10n_nl_mis_reports-13.0.1.1.0.dist-info/top_level.txt
odoo13_addon_l10n_nl_mis_reports-13.0.1.1.0.dist-info/RECORD
